README.md
setup.cfg
setup.py
wwpdb/__init__.py
wwpdb.apps.workmanager.egg-info/PKG-INFO
wwpdb.apps.workmanager.egg-info/SOURCES.txt
wwpdb.apps.workmanager.egg-info/dependency_links.txt
wwpdb.apps.workmanager.egg-info/not-zip-safe
wwpdb.apps.workmanager.egg-info/requires.txt
wwpdb.apps.workmanager.egg-info/top_level.txt
wwpdb/apps/__init__.py
wwpdb/apps/workmanager/__init__.py
wwpdb/apps/workmanager/db_access/ContentDbApi.py
wwpdb/apps/workmanager/db_access/DBLoader.py
wwpdb/apps/workmanager/db_access/DbApiUtil.py
wwpdb/apps/workmanager/db_access/StatsUtil.py
wwpdb/apps/workmanager/db_access/StatusDbApi.py
wwpdb/apps/workmanager/db_access/__init__.py
wwpdb/apps/workmanager/depict/DepictBase.py
wwpdb/apps/workmanager/depict/DepictContent.py
wwpdb/apps/workmanager/depict/DepictGroup.py
wwpdb/apps/workmanager/depict/DepictLevel1.py
wwpdb/apps/workmanager/depict/DepictOther.py
wwpdb/apps/workmanager/depict/DepictSnapShot.py
wwpdb/apps/workmanager/depict/DepictWorkFlow.py
wwpdb/apps/workmanager/depict/Level1Util.py
wwpdb/apps/workmanager/depict/ReadConFigFile.py
wwpdb/apps/workmanager/depict/SearchUtil.py
wwpdb/apps/workmanager/depict/ServerInfoUtil.py
wwpdb/apps/workmanager/depict/__init__.py
wwpdb/apps/workmanager/file_access/AnnotAssignUtil.py
wwpdb/apps/workmanager/file_access/CopyFileToAutoGroup.py
wwpdb/apps/workmanager/file_access/LogFileUtil.py
wwpdb/apps/workmanager/file_access/MileStoneFile.py
wwpdb/apps/workmanager/file_access/SnapShotDiff.py
wwpdb/apps/workmanager/file_access/__init__.py
wwpdb/apps/workmanager/task_access/BaseClass.py
wwpdb/apps/workmanager/task_access/CifChecker.py
wwpdb/apps/workmanager/task_access/LigandFinder.py
wwpdb/apps/workmanager/task_access/MetaDataEditor.py
wwpdb/apps/workmanager/task_access/MetaDataMerger.py
wwpdb/apps/workmanager/task_access/PdbFileGenerator.py
wwpdb/apps/workmanager/task_access/SequenceMerger.py
wwpdb/apps/workmanager/task_access/StatusUpdater.py
wwpdb/apps/workmanager/task_access/__init__.py
wwpdb/apps/workmanager/utils/LoadRemindMessageTrack.py
wwpdb/apps/workmanager/utils/ManageSite.py
wwpdb/apps/workmanager/utils/__init__.py
wwpdb/apps/workmanager/webapp/WorkManagerWebApp.py
wwpdb/apps/workmanager/webapp/__init__.py
wwpdb/apps/workmanager/workflow_access/OrderedDict.py
