Metadata-Version: 2.4
Name: wwpdb.apps.workmanager
Version: 0.26.1
Summary: wwPDB workflow manager app
Home-page: https://github.com/rcsb/py-wwpdb_apps_workmanager
Author: Ezra Peisach
Author-email: ezra.peisach@rcsb.org
License: Apache 2.0
Classifier: Development Status :: 3 - Alpha
Classifier: Intended Audience :: Developers
Classifier: Natural Language :: English
Classifier: License :: OSI Approved :: Apache Software License
Classifier: Programming Language :: Python
Classifier: Programming Language :: Python :: 2.7
Classifier: Programming Language :: Python :: 3
Classifier: Programming Language :: Python :: 3.6
Classifier: Programming Language :: Python :: 3.7
Requires-Dist: wwpdb.utils.config<2.0,>=0.27
Requires-Dist: wwpdb.utils.wf
Requires-Dist: wwpdb.io<2.0,>=0.6
Requires-Dist: rcsb.utils.multiproc
Requires-Dist: wwpdb.apps.wf_engine>=0.5
Requires-Dist: wwpdb.apps.msgmodule~=0.180
Requires-Dist: wwpdb.utils.db>=0.4
Requires-Dist: wwpdb.utils.session>=0.3
Requires-Dist: mmcif.utils
Requires-Dist: wwpdb.utils.detach~=0.3
Requires-Dist: mysqlclient
Provides-Extra: dev
Requires-Dist: check-manifest; extra == "dev"
Provides-Extra: test
Requires-Dist: coverage; extra == "test"
Dynamic: author
Dynamic: author-email
Dynamic: classifier
Dynamic: description
Dynamic: home-page
Dynamic: license
Dynamic: provides-extra
Dynamic: requires-dist
Dynamic: summary
